wavytool/__init__.py
wavytool/__main__.py
wavytool/core_wavy.py
wavytool/dlg_wav2dat.py
wavytool/example-plot.py
wavytool/gui_wav2dat.py
wavytool/gui_wavy.py
wavytool/mw_wav2dat.py
wavytool/mw_wavy.py
wavytool/images/__init__.py
wavytool/images/rc_wavy_rc.py
wavytool-2.1.dist-info/METADATA
wavytool-2.1.dist-info/RECORD
wavytool-2.1.dist-info/WHEEL
wavytool-2.1.dist-info/entry_points.txt
wavytool-2.1.dist-info/top_level.txt
