Metadata-Version: 2.1
Name: wavytool
Version: 2.1
Summary: Simple GUI that acquires data from input devices, plot and export files.
Home-page: https://github.com/dpizetta/wavy
Author: Daniel Cosmo Pizetta
Author-email: daniel.pizett@usp.br
License: UNKNOWN
Platform: UNKNOWN
Classifier: Development Status :: 4 - Beta
Classifier: Intended Audience :: End Users/Desktop
Classifier: Intended Audience :: Developers
Classifier: Operating System :: Microsoft :: Windows
Classifier: Operating System :: POSIX
Classifier: Programming Language :: Python
Requires-Dist: qtpy (>=1.4)
Requires-Dist: numpy (>=1.13)
Requires-Dist: pyqtgraph (>=0.10)
Requires-Dist: pyaudio (>=0.2)
